setup.py
users/__init__.py
users/admin.py
users/forms.py
users/listeners.py
users/managers.py
users/models.py
users/tests.py
users/urls.py
users/utils.py
users/views.py
zero_users.egg-info/PKG-INFO
zero_users.egg-info/SOURCES.txt
zero_users.egg-info/dependency_links.txt
zero_users.egg-info/not-zip-safe
zero_users.egg-info/requires.txt
zero_users.egg-info/top_level.txt