Metadata-Version: 1.0
Name: zero-users
Version: 0.1.4
Summary: Simple app with views and models to manage users and profiles
Home-page: http://github.com/mandlaweb/Zero-Users
Author: Jose Maria Zambrana Arze
Author-email: contact@josezambrana.com
License: apache license v2.0
Keywords: zero users app
Platform: UNKNOWN
